ec2instanceconnectcli/EC2InstanceConnectCLI.py
ec2instanceconnectcli/EC2InstanceConnectCommand.py
ec2instanceconnectcli/EC2InstanceConnectKey.py
ec2instanceconnectcli/EC2InstanceConnectLogger.py
ec2instanceconnectcli/__init__.py
ec2instanceconnectcli/ec2_util.py
ec2instanceconnectcli/input_parser.py
ec2instanceconnectcli/key_publisher.py
ec2instanceconnectcli/key_utils.py
ec2instanceconnectcli/mops.py
ec2instanceconnectcli/mputty.py
ec2instanceconnectcli-1.0.3.data/scripts/msftp
ec2instanceconnectcli-1.0.3.data/scripts/msftp-putty.cmd
ec2instanceconnectcli-1.0.3.data/scripts/msftp.cmd
ec2instanceconnectcli-1.0.3.data/scripts/mssh
ec2instanceconnectcli-1.0.3.data/scripts/mssh-putty.cmd
ec2instanceconnectcli-1.0.3.data/scripts/mssh.cmd
ec2instanceconnectcli-1.0.3.dist-info/LICENSE
ec2instanceconnectcli-1.0.3.dist-info/METADATA
ec2instanceconnectcli-1.0.3.dist-info/NOTICE
ec2instanceconnectcli-1.0.3.dist-info/WHEEL
ec2instanceconnectcli-1.0.3.dist-info/top_level.txt
ec2instanceconnectcli-1.0.3.dist-info/RECORD
