Metadata-Version: 2.1
Name: ec2instanceconnectcli
Version: 1.0.3
Summary: Command Line Interface for AWS EC2 Instance Connect
Home-page: https://docs.aws.amazon.com/AWSEC2/latest/UserGuide/Connect-using-EC2-Instance-Connect.html
Author: Amazon Web Services
License: Apache License 2.0
Classifier: Development Status :: 5 - Production/Stable
Classifier: Environment :: Console
Classifier: Intended Audience :: Developers
Classifier: Intended Audience :: System Administrators
Classifier: Natural Language :: English
Classifier: License :: OSI Approved :: Apache Software License
Classifier: Operating System :: Microsoft :: Windows
Classifier: Operating System :: OS Independent
Classifier: Operating System :: Unix
Classifier: Programming Language :: Python
Classifier: Programming Language :: Python :: 3
Classifier: Programming Language :: Python :: 3.6
Classifier: Programming Language :: Python :: 3.7
Classifier: Programming Language :: Python :: 3.8
Classifier: Topic :: Internet :: File Transfer Protocol (FTP)
Classifier: Topic :: System :: Systems Administration :: Authentication/Directory
License-File: LICENSE
License-File: NOTICE
Requires-Dist: cryptography (>=39.0.1)
Requires-Dist: botocore (>=1.12.179)
